{
  "a11y.close_search": "Luk søgning",
  "a11y.edit_link": "Rediger link",
  "a11y.format_text": "Formater tekst",
  "a11y.insert_block": "Indsæt blok",
  "a11y.main_toolbar": "Hovedværktøjslinje",
  "a11y.next_match": "Næste match",
  "a11y.previous_match": "Forrige match",
  "a11y.search_in_document": "Søg i dokumentet",
  "a11y.search_text": "Søgetekst",
  "a11y.select_language": "Vælg sprog",
  "a11y.sidebar": "Sidepanel",
  "a11y.skip_to_content": "Spring til indhold",
  "common.close": "Luk",
  "common.file": "Fil",
  "common.open": "Åbn",
  "context.copy": "Kopiér",
  "context.copy_image_address": "Kopiér billedadresse",
  "context.copy_link": "Kopiér link",
  "context.cut": "Klip",
  "context.open_link": "Åbn link",
  "context.paste": "Sæt ind",
  "context.paste_plain": "Sæt ind som ren tekst",
  "context.select_all": "Markér alt",
  "dialog.cancel": "Annuller",
  "dialog.discard": "Kassér",
  "dialog.dont_save": "Gem ikke",
  "dialog.save": "Gem",
  "dialog.unsaved_close": "Du har ikke-gemte ændringer. Vil du gemme, før du lukker?",
  "dialog.unsaved_exit_edit": "Du har ikke-gemte ændringer. Vil du gemme, før du forlader redigeringstilstand?",
  "dialog.unsaved_new_file": "Du har ikke-gemte ændringer. Vil du gemme, før du opretter en ny fil?",
  "dialog.unsaved_open_file": "Du har ugemte ændringer. Vil du gemme, før du åbner en ny fil?",
  "dialog.unsaved_title": "Ugemte ændringer",
  "drop_zone.text": "Træk din Markdown-fil hertil",
  "export.open": "Åbn",
  "export.success": "PDF-filen blev eksporteret med succes",
  "format.block_type": "Bloktype",
  "format.blockquote": "Blokcitat",
  "format.bold": "Fed ({mod}+B)",
  "format.bullet_list": "Punktopstilling",
  "format.code": "Indlejret kode ({mod}+E)",
  "format.code_block": "Kodeblok",
  "format.divider": "Skillelinje",
  "format.heading1": "Overskrift 1",
  "format.heading2": "Overskrift 2",
  "format.heading3": "Overskrift 3",
  "format.heading4": "Overskrift 4",
  "format.heading5": "Overskrift 5",
  "format.image": "Billede",
  "format.image_upload": "Upload fra computer",
  "format.image_url": "Billed-URL",
  "format.italic": "Kursiv ({mod}+I)",
  "format.link": "Link ({mod}+K)",
  "format.lists": "Lister",
  "format.more_elements": "Mere",
  "format.numbered_list": "Nummereret liste",
  "format.paragraph": "Afsnit",
  "format.strikethrough": "Gennemstreget ({mod}+Shift+X)",
  "format.table": "Tabel",
  "format.task_list": "Opgaveliste",
  "format.text_formatting": "Tekstformatering",
  "format.underline": "Understreg ({mod}+U)",
  "help.editing": "Redigering",
  "help.fallback_notice": "Denne side er endnu ikke tilgængelig på dit sprog. Viser den engelske version.",
  "help.features": "Funktioner",
  "help.getting_started": "Kom i gang",
  "help.shortcuts": "Tastaturgenveje",
  "image.delete": "Slet billede",
  "image.edit": "Rediger billed-URL",
  "image_dialog.alt_placeholder": "Billedbeskrivelse",
  "image_dialog.insert": "Indsæt",
  "image_dialog.title": "Indsæt billed-URL",
  "image_dialog.url_placeholder": "https://example.com/image.png",
  "lang_picker.filter_label": "Filtrer sprog",
  "lang_picker.filter_placeholder": "Filtrer sprog...",
  "lang_picker.plain_text": "Almindelig tekst",
  "link.apply": "Anvend link",
  "link.cancel": "Annuller",
  "link.display_text": "Vist tekst",
  "link.edit": "Rediger",
  "link.edit_link": "Rediger link",
  "link.remove_link": "Fjern link",
  "link.text": "Tekst",
  "link.text_placeholder": "Vist tekst (valgfri)",
  "link.url": "URL",
  "link.url_placeholder": "Indsæt eller skriv URL...",
  "mermaid.done": "Færdig",
  "mermaid.edit": "Rediger",
  "mermaid.error_prefix": "Syntaksfejl",
  "mermaid.stale": "Forhåndsvisning forældet",
  "recovery.discard": "Kassér",
  "recovery.message": "Kern fandt ikke-gemte ændringer fra en tidligere session. Vil du gendanne dem?",
  "recovery.restore": "Gendan",
  "recovery.title": "Gendan ugemte ændringer?",
  "search.count": "resultater",
  "search.no_results": "Ingen resultater",
  "search.placeholder": "Søg i dokument...",
  "settings.language": "Sprog",
  "settings.theme": "Tema",
  "settings.theme_dark": "Mørk",
  "settings.theme_light": "Lys",
  "settings.theme_system": "System",
  "sidebar.no_headings": "Ingen overskrifter fundet",
  "sidebar.recent": "Seneste filer",
  "sidebar.toc": "Indholdsfortegnelse",
  "slash.blockquote": "Citatblok",
  "slash.blockquote_desc": "Citatblok",
  "slash.bullet_list": "Punktopstilling",
  "slash.bullet_list_desc": "Uordnet liste",
  "slash.code_block": "Kodeblok",
  "slash.code_block_desc": "Kodeblok",
  "slash.divider": "Skillelinje",
  "slash.divider_desc": "Vandret streg",
  "slash.heading1": "Overskrift 1",
  "slash.heading1_desc": "Stor overskrift",
  "slash.heading2": "Overskrift 2",
  "slash.heading2_desc": "Mellemstor overskrift",
  "slash.heading3": "Overskrift 3",
  "slash.heading3_desc": "Lille overskrift",
  "slash.heading4": "Overskrift 4",
  "slash.heading4_desc": "Mindre overskrift",
  "slash.heading5": "Overskrift 5",
  "slash.heading5_desc": "Mindste overskrift",
  "slash.image_upload": "Upload billede",
  "slash.image_upload_desc": "Upload fra computer",
  "slash.image_url": "Billed-URL",
  "slash.image_url_desc": "Indlejr fra URL",
  "slash.mermaid": "Mermaid-diagram",
  "slash.mermaid_desc": "Indsæt et diagram",
  "slash.no_results": "Ingen resultater",
  "slash.numbered_list": "Nummereret liste",
  "slash.numbered_list_desc": "Ordnet liste",
  "slash.paragraph": "Afsnit",
  "slash.paragraph_desc": "Almindelig tekst",
  "slash.table": "Tabel",
  "slash.table_desc": "3×3 tabel",
  "slash.task_list": "Opgaveliste",
  "slash.task_list_desc": "Tjekliste",
  "table.add_col_left": "Tilføj kolonne til venstre",
  "table.add_col_right": "Tilføj kolonne til højre",
  "table.add_row_above": "Tilføj række ovenfor",
  "table.add_row_below": "Tilføj række nedenfor",
  "table.col_options": "Kolonne {n} indstillinger",
  "table.delete_col": "Slet kolonne",
  "table.delete_row": "Slet række",
  "table.delete_table": "Slet tabel",
  "table.header": "Overskrift",
  "table.insert_col_left": "Indsæt kolonne til venstre",
  "table.insert_col_right": "Indsæt kolonne til højre",
  "table.insert_row_above": "Indsæt række ovenfor",
  "table.insert_row_below": "Indsæt række nedenfor",
  "table.new_row": "+ Ny række",
  "table.row_options": "Indstillinger for række {n}",
  "toolbar.cursor_sync": "Skift cursorsynkronisering",
  "toolbar.edit": "Rediger",
  "toolbar.empty_line_hint": "Skriv / for at indsætte",
  "toolbar.export_pdf": "Eksporter PDF",
  "toolbar.focus": "Fokustilstand",
  "toolbar.more": "Mere",
  "toolbar.new_file": "Ny fil",
  "toolbar.open": "Åbn fil",
  "toolbar.print": "Udskriv",
  "toolbar.reader": "Læser",
  "toolbar.save": "Gem",
  "toolbar.search": "Søg",
  "toolbar.settings": "Indstillinger",
  "toolbar.split_view": "Opdelt visning",
  "toolbar.switch_to_edit": "Skift til redigeringstilstand",
  "toolbar.switch_to_reader": "Skift til læsetilstand",
  "toolbar.theme": "Skift mørkt/lyst tema",
  "toolbar.toc": "Indholdsfortegnelse",
  "toolbar.zoom_in": "Zoom ind",
  "toolbar.zoom_out": "Zoom ud",
  "toolbar.zoom_reset": "Nulstil zoom",
  "trial.days_remaining": "{days} dage tilbage af prøveperioden",
  "trial.expired_message": "Din prøveperiode er udløbet. Køb Kern for at fortsætte med at redigere.",
  "trial.feature_edit": "Rediger Markdown med WYSIWYG og delt visning",
  "trial.feature_export": "Eksporter til PDF",
  "trial.feature_save": "Gem og opret nye filer",
  "trial.one_time_purchase": "Engangskøb. Intet abonnement.",
  "trial.purchase_button": "Køb Kern",
  "trial.purchase_desc": "Få fuld adgang til alle redigerings- og eksportfunktioner med et engangskøb.",
  "trial.purchase_title": "Lås Kern op",
  "trial.purchasing": "Køber...",
  "trial.restore_purchases": "Gendan køb",
  "trial.restoring": "Gendanner...",
  "viewer.copied": "Kopieret!",
  "viewer.copy": "Kopiér",
  "welcome.drop_hint": "eller træk og slip en .md-fil",
  "welcome.new_button": "Ny fil",
  "welcome.open_button": "Åbn fil",
  "welcome.subtitle": "En smuk Markdown-fremviser",
  "welcome.title": "Kern",
  "table.copy_col": "Kopiér kolonne",
  "table.copy_row": "Kopiér række",
  "table.cut_col": "Klip kolonne",
  "table.cut_row": "Klip række",
  "table.paste_col": "Indsæt kolonne til højre",
  "table.paste_row": "Indsæt række under"
}